{"GlobalPropertiesHash":"2ilJ2M8+ZdH0swl4cXFj9Ji8kay0R08ISE/fEc+OL0o=","FingerprintPatternsHash":"8ZRc1sGeVrPBx4lD717BgRaQekyh78QKV9SKsdt638U=","PropertyOverridesHash":"8ZRc1sGeVrPBx4lD717BgRaQekyh78QKV9SKsdt638U=","InputHashes":["T3EhxVJsBal93OyoLn5Yb9vRulkJLxMPtQvZu6rGmSc=","X4S9hy/Tp4E9uSFdn\u002BJe\u002BwHCnUnXaqjp1x5ibJBrF/s=","aVXCp5Yu0mSQm35BGj9DwNlQa4vRv8G71ser6lrYu7E=","1O7FfI2Tk68CHXhKzOdFyqxoa7kWUb0nYP9r9qq7fD0=","rQjC\u002BS5jIhP1WMa64V1KU2mjWCG1BxlOsJ4741sFHQ0=","8zySZOv6i2iXFfm8BxIq/5XahNdfZGloznn\u002B3UxmWSQ=","SEsDt1JUlzfQm\u002BrzpV8BHXq\u002BKnljQhQKQFNxX0ICiGU=","Mquj9KBWN\u002BlJ/gPuzyKwH87YofHtu4ECIeSeI6vz2Ew=","pO7buuSDVpmCC7XEfVKK3UPv7TQ0oS72G52vbExYVUI="],"CachedAssets":{"T3EhxVJsBal93OyoLn5Yb9vRulkJLxMPtQvZu6rGmSc=":{"Identity":"/Users/hasbeejay/Desktop/Github Repos/LawFlow/obj/Debug/net10.0/compressed/tzxjg6is5z-{0}-6x2ajsl5c8-6x2ajsl5c8.gz","SourceId":"MudBlazor","SourceType":"Package","ContentRoot":"/Users/hasbeejay/Desktop/Github Repos/LawFlow/obj/Debug/net10.0/compressed/","BasePath":"_content/MudBlazor","RelativePath":"MudBlazor.min.css.gz","AssetKind":"All","AssetMode":"All","AssetRole":"Alternative","AssetMergeBehavior":null,"AssetMergeSource":"","RelatedAsset":"/Users/hasbeejay/.nuget/packages/mudblazor/9.4.0/staticwebassets/MudBlazor.min.css","AssetTraitName":"Content-Encoding","AssetTraitValue":"gzip","Fingerprint":"ittzqziwsa","Integrity":"tmczO28EalUcbVehGfpKW0Ax1oD2SKq1MaYvJMyGJZQ=","CopyToOutputDirectory":"Never","CopyToPublishDirectory":"PreserveNewest","OriginalItemSpec":"/Users/hasbeejay/.nuget/packages/mudblazor/9.4.0/staticwebassets/MudBlazor.min.css","FileLength":65201,"LastWriteTime":"2026-05-27T05:47:59.5244288+00:00"},"X4S9hy/Tp4E9uSFdn\u002BJe\u002BwHCnUnXaqjp1x5ibJBrF/s=":{"Identity":"/Users/hasbeejay/Desktop/Github Repos/LawFlow/obj/Debug/net10.0/compressed/0wz98yz2xy-{0}-jolev99wdd-jolev99wdd.gz","SourceId":"MudBlazor","SourceType":"Package","ContentRoot":"/Users/hasbeejay/Desktop/Github Repos/LawFlow/obj/Debug/net10.0/compressed/","BasePath":"_content/MudBlazor","RelativePath":"MudBlazor.min.js.gz","AssetKind":"All","AssetMode":"All","AssetRole":"Alternative","AssetMergeBehavior":null,"AssetMergeSource":"","RelatedAsset":"/Users/hasbeejay/.nuget/packages/mudblazor/9.4.0/staticwebassets/MudBlazor.min.js","AssetTraitName":"Content-Encoding","AssetTraitValue":"gzip","Fingerprint":"kc0st886kp","Integrity":"xE32EY9N1aRscZ4MAzMupW0Z3BzpCed7VhiPeMFZq80=","CopyToOutputDirectory":"Never","CopyToPublishDirectory":"PreserveNewest","OriginalItemSpec":"/Users/hasbeejay/.nuget/packages/mudblazor/9.4.0/staticwebassets/MudBlazor.min.js","FileLength":16426,"LastWriteTime":"2026-05-27T05:47:59.5110613+00:00"},"aVXCp5Yu0mSQm35BGj9DwNlQa4vRv8G71ser6lrYu7E=":{"Identity":"/Users/hasbeejay/Desktop/Github Repos/LawFlow/obj/Debug/net10.0/compressed/o7k4cxtn0u-{0}-h82a7aihv0-h82a7aihv0.gz","SourceId":"MudBlazor","SourceType":"Package","ContentRoot":"/Users/hasbeejay/Desktop/Github Repos/LawFlow/obj/Debug/net10.0/compressed/","BasePath":"_content/MudBlazor","RelativePath":"MudBlazor.min.js.map.gz","AssetKind":"All","AssetMode":"All","AssetRole":"Alternative","AssetMergeBehavior":null,"AssetMergeSource":"","RelatedAsset":"/Users/hasbeejay/.nuget/packages/mudblazor/9.4.0/staticwebassets/MudBlazor.min.js.map","AssetTraitName":"Content-Encoding","AssetTraitValue":"gzip","Fingerprint":"j8b4yfwql5","Integrity":"44931L8u6g9ELYC8nM3hh8BNulBmuFEitefyelniTik=","CopyToOutputDirectory":"Never","CopyToPublishDirectory":"PreserveNewest","OriginalItemSpec":"/Users/hasbeejay/.nuget/packages/mudblazor/9.4.0/staticwebassets/MudBlazor.min.js.map","FileLength":51436,"LastWriteTime":"2026-05-27T05:47:59.5208367+00:00"},"1O7FfI2Tk68CHXhKzOdFyqxoa7kWUb0nYP9r9qq7fD0=":{"Identity":"/Users/hasbeejay/Desktop/Github Repos/LawFlow/obj/Debug/net10.0/compressed/o4b58mm576-{0}-8z7y5mf7fj-8z7y5mf7fj.gz","SourceId":"LawFlow","SourceType":"Discovered","ContentRoot":"/Users/hasbeejay/Desktop/Github Repos/LawFlow/obj/Debug/net10.0/compressed/","BasePath":"/","RelativePath":"css/lf#[.{fingerprint=8z7y5mf7fj}]?.css.gz","AssetKind":"All","AssetMode":"All","AssetRole":"Alternative","AssetMergeBehavior":null,"AssetMergeSource":"","RelatedAsset":"/Users/hasbeejay/Desktop/Github Repos/LawFlow/wwwroot/css/lf.css","AssetTraitName":"Content-Encoding","AssetTraitValue":"gzip","Fingerprint":"ao7kfcb6rn","Integrity":"2rJQNLo4nZdRFQBYxVjhjl/8D\u002BAHrfbEq8JYL1LLI6c=","CopyToOutputDirectory":"Never","CopyToPublishDirectory":"PreserveNewest","OriginalItemSpec":"/Users/hasbeejay/Desktop/Github Repos/LawFlow/wwwroot/css/lf.css","FileLength":9151,"LastWriteTime":"2026-05-27T08:28:44.6914188+00:00"},"rQjC\u002BS5jIhP1WMa64V1KU2mjWCG1BxlOsJ4741sFHQ0=":{"Identity":"/Users/hasbeejay/Desktop/Github Repos/LawFlow/obj/Debug/net10.0/compressed/se26rdiey6-{0}-g0fkdtumun-g0fkdtumun.gz","SourceId":"LawFlow","SourceType":"Discovered","ContentRoot":"/Users/hasbeejay/Desktop/Github Repos/LawFlow/obj/Debug/net10.0/compressed/","BasePath":"/","RelativePath":"app#[.{fingerprint=g0fkdtumun}]?.css.gz","AssetKind":"All","AssetMode":"All","AssetRole":"Alternative","AssetMergeBehavior":null,"AssetMergeSource":"","RelatedAsset":"/Users/hasbeejay/Desktop/Github Repos/LawFlow/wwwroot/app.css","AssetTraitName":"Content-Encoding","AssetTraitValue":"gzip","Fingerprint":"yhg5eopvrn","Integrity":"Op98FLL5FrfPi1Io2mA6G\u002BPAXT/fcrupQE4R\u002Bn6V1yU=","CopyToOutputDirectory":"Never","CopyToPublishDirectory":"PreserveNewest","OriginalItemSpec":"/Users/hasbeejay/Desktop/Github Repos/LawFlow/wwwroot/app.css","FileLength":3357,"LastWriteTime":"2026-05-27T09:10:17.0375551+00:00"},"8zySZOv6i2iXFfm8BxIq/5XahNdfZGloznn\u002B3UxmWSQ=":{"Identity":"/Users/hasbeejay/Desktop/Github Repos/LawFlow/obj/Debug/net10.0/compressed/0ihnqj2b8x-{0}-ej96puwv3k-ej96puwv3k.gz","SourceId":"LawFlow","SourceType":"Discovered","ContentRoot":"/Users/hasbeejay/Desktop/Github Repos/LawFlow/obj/Debug/net10.0/compressed/","BasePath":"/","RelativePath":"_framework/blazor.web#[.{fingerprint=ej96puwv3k}]?.js.gz","AssetKind":"All","AssetMode":"CurrentProject","AssetRole":"Alternative","AssetMergeBehavior":null,"AssetMergeSource":"","RelatedAsset":"/Users/hasbeejay/.nuget/packages/microsoft.aspnetcore.app.internal.assets/10.0.8/_framework/blazor.web.js","AssetTraitName":"Content-Encoding","AssetTraitValue":"gzip","Fingerprint":"h2zioq5bjc","Integrity":"962rgHYVc8K5rj6WA0821oKuSrO4lLy4t7nybIkvmx4=","CopyToOutputDirectory":"Never","CopyToPublishDirectory":"PreserveNewest","OriginalItemSpec":"/Users/hasbeejay/.nuget/packages/microsoft.aspnetcore.app.internal.assets/10.0.8/_framework/blazor.web.js","FileLength":55633,"LastWriteTime":"2026-05-27T05:47:59.5199574+00:00"},"SEsDt1JUlzfQm\u002BrzpV8BHXq\u002BKnljQhQKQFNxX0ICiGU=":{"Identity":"/Users/hasbeejay/Desktop/Github Repos/LawFlow/obj/Debug/net10.0/compressed/zxp4s0uvjp-{0}-cj5793hgrt-cj5793hgrt.gz","SourceId":"LawFlow","SourceType":"Discovered","ContentRoot":"/Users/hasbeejay/Desktop/Github Repos/LawFlow/obj/Debug/net10.0/compressed/","BasePath":"/","RelativePath":"_framework/blazor.server#[.{fingerprint=cj5793hgrt}]?.js.gz","AssetKind":"All","AssetMode":"CurrentProject","AssetRole":"Alternative","AssetMergeBehavior":null,"AssetMergeSource":"","RelatedAsset":"/Users/hasbeejay/.nuget/packages/microsoft.aspnetcore.app.internal.assets/10.0.8/_framework/blazor.server.js","AssetTraitName":"Content-Encoding","AssetTraitValue":"gzip","Fingerprint":"yjmrpsu4sm","Integrity":"EszwUgcutf3xEYpnzCs/3tQRbtR8u9zPZDOop8lgGWY=","CopyToOutputDirectory":"Never","CopyToPublishDirectory":"PreserveNewest","OriginalItemSpec":"/Users/hasbeejay/.nuget/packages/microsoft.aspnetcore.app.internal.assets/10.0.8/_framework/blazor.server.js","FileLength":44622,"LastWriteTime":"2026-05-27T05:47:59.5140182+00:00"},"Mquj9KBWN\u002BlJ/gPuzyKwH87YofHtu4ECIeSeI6vz2Ew=":{"Identity":"/Users/hasbeejay/Desktop/Github Repos/LawFlow/obj/Debug/net10.0/compressed/3n0ncg9rax-{0}-ap51uywg3a-ap51uywg3a.gz","SourceId":"LawFlow","SourceType":"Computed","ContentRoot":"/Users/hasbeejay/Desktop/Github Repos/LawFlow/obj/Debug/net10.0/compressed/","BasePath":"/","RelativePath":"LawFlow#[.{fingerprint=ap51uywg3a}]?.styles.css.gz","AssetKind":"All","AssetMode":"CurrentProject","AssetRole":"Alternative","AssetMergeBehavior":null,"AssetMergeSource":"","RelatedAsset":"/Users/hasbeejay/Desktop/Github Repos/LawFlow/obj/Debug/net10.0/scopedcss/bundle/LawFlow.styles.css","AssetTraitName":"Content-Encoding","AssetTraitValue":"gzip","Fingerprint":"yjf8xri6tf","Integrity":"vq3wp1p3BKZt85C3K\u002BvpvmqtitbFLOMpze04A8yvwHo=","CopyToOutputDirectory":"Never","CopyToPublishDirectory":"PreserveNewest","OriginalItemSpec":"/Users/hasbeejay/Desktop/Github Repos/LawFlow/obj/Debug/net10.0/scopedcss/bundle/LawFlow.styles.css","FileLength":288,"LastWriteTime":"2026-05-27T05:47:59.5081499+00:00"},"pO7buuSDVpmCC7XEfVKK3UPv7TQ0oS72G52vbExYVUI=":{"Identity":"/Users/hasbeejay/Desktop/Github Repos/LawFlow/obj/Debug/net10.0/compressed/z1cyszk5vn-{0}-ap51uywg3a-ap51uywg3a.gz","SourceId":"LawFlow","SourceType":"Computed","ContentRoot":"/Users/hasbeejay/Desktop/Github Repos/LawFlow/obj/Debug/net10.0/compressed/","BasePath":"/","RelativePath":"LawFlow#[.{fingerprint=ap51uywg3a}]!.bundle.scp.css.gz","AssetKind":"All","AssetMode":"Reference","AssetRole":"Alternative","AssetMergeBehavior":null,"AssetMergeSource":"","RelatedAsset":"/Users/hasbeejay/Desktop/Github Repos/LawFlow/obj/Debug/net10.0/scopedcss/projectbundle/LawFlow.bundle.scp.css","AssetTraitName":"Content-Encoding","AssetTraitValue":"gzip","Fingerprint":"yjf8xri6tf","Integrity":"vq3wp1p3BKZt85C3K\u002BvpvmqtitbFLOMpze04A8yvwHo=","CopyToOutputDirectory":"Never","CopyToPublishDirectory":"PreserveNewest","OriginalItemSpec":"/Users/hasbeejay/Desktop/Github Repos/LawFlow/obj/Debug/net10.0/scopedcss/projectbundle/LawFlow.bundle.scp.css","FileLength":288,"LastWriteTime":"2026-05-27T05:47:59.5070464+00:00"}},"CachedCopyCandidates":{}}